{"nodes": [{"id": "c_users_yashb_pictures_projects_testbuddy_frontend_src_components_theme_themeprovider_tsx", "label": "ThemeProvider.tsx", "file_type": "code", "source_file": "C:\\Users\\yashb\\Pictures\\Projects\\TestBuddy\\Frontend\\src\\components\\theme\\ThemeProvider.tsx", "source_location": "L1"}, {"id": "themeprovider_getinitialtheme", "label": "getInitialTheme()", "file_type": "code", "source_file": "C:\\Users\\yashb\\Pictures\\Projects\\TestBuddy\\Frontend\\src\\components\\theme\\ThemeProvider.tsx", "source_location": "L14"}, {"id": "themeprovider_themeprovider", "label": "ThemeProvider()", "file_type": "code", "source_file": "C:\\Users\\yashb\\Pictures\\Projects\\TestBuddy\\Frontend\\src\\components\\theme\\ThemeProvider.tsx", "source_location": "L20"}], "edges": [{"source": "c_users_yashb_pictures_projects_testbuddy_frontend_src_components_theme_themeprovider_tsx", "target": "react", "relation": "imports_from", "confidence": "EXTRACTED", "source_file": "C:\\Users\\yashb\\Pictures\\Projects\\TestBuddy\\Frontend\\src\\components\\theme\\ThemeProvider.tsx", "source_location": "L1", "weight": 1.0}, {"source": "c_users_yashb_pictures_projects_testbuddy_frontend_src_components_theme_themeprovider_tsx", "target": "themeprovider_getinitialtheme", "relation": "contains", "confidence": "EXTRACTED", "source_file": "C:\\Users\\yashb\\Pictures\\Projects\\TestBuddy\\Frontend\\src\\components\\theme\\ThemeProvider.tsx", "source_location": "L14", "weight": 1.0}, {"source": "c_users_yashb_pictures_projects_testbuddy_frontend_src_components_theme_themeprovider_tsx", "target": "themeprovider_themeprovider", "relation": "contains", "confidence": "EXTRACTED", "source_file": "C:\\Users\\yashb\\Pictures\\Projects\\TestBuddy\\Frontend\\src\\components\\theme\\ThemeProvider.tsx", "source_location": "L20", "weight": 1.0}], "raw_calls": [{"caller_nid": "themeprovider_getinitialtheme", "callee": "getItem", "source_file": "C:\\Users\\yashb\\Pictures\\Projects\\TestBuddy\\Frontend\\src\\components\\theme\\ThemeProvider.tsx", "source_location": "L16"}, {"caller_nid": "themeprovider_themeprovider", "callee": "useState", "source_file": "C:\\Users\\yashb\\Pictures\\Projects\\TestBuddy\\Frontend\\src\\components\\theme\\ThemeProvider.tsx", "source_location": "L21"}, {"caller_nid": "themeprovider_themeprovider", "callee": "useEffect", "source_file": "C:\\Users\\yashb\\Pictures\\Projects\\TestBuddy\\Frontend\\src\\components\\theme\\ThemeProvider.tsx", "source_location": "L23"}, {"caller_nid": "themeprovider_themeprovider", "callee": "useMemo", "source_file": "C:\\Users\\yashb\\Pictures\\Projects\\TestBuddy\\Frontend\\src\\components\\theme\\ThemeProvider.tsx", "source_location": "L29"}, {"caller_nid": "themeprovider_themeprovider", "callee": "useContext", "source_file": "C:\\Users\\yashb\\Pictures\\Projects\\TestBuddy\\Frontend\\src\\components\\theme\\ThemeProvider.tsx", "source_location": "L35"}]}