{"nodes": [{"id": "c_users_yashb_pictures_projects_testbuddy_frontend_src_components_navlink_tsx", "label": "NavLink.tsx", "file_type": "code", "source_file": "C:\\Users\\yashb\\Pictures\\Projects\\TestBuddy\\Frontend\\src\\components\\NavLink.tsx", "source_location": "L1"}], "edges": [{"source": "c_users_yashb_pictures_projects_testbuddy_frontend_src_components_navlink_tsx", "target": "react_router_dom", "relation": "imports_from", "confidence": "EXTRACTED", "source_file": "C:\\Users\\yashb\\Pictures\\Projects\\TestBuddy\\Frontend\\src\\components\\NavLink.tsx", "source_location": "L1", "weight": 1.0}, {"source": "c_users_yashb_pictures_projects_testbuddy_frontend_src_components_navlink_tsx", "target": "react", "relation": "imports_from", "confidence": "EXTRACTED", "source_file": "C:\\Users\\yashb\\Pictures\\Projects\\TestBuddy\\Frontend\\src\\components\\NavLink.tsx", "source_location": "L2", "weight": 1.0}, {"source": "c_users_yashb_pictures_projects_testbuddy_frontend_src_components_navlink_tsx", "target": "utils", "relation": "imports_from", "confidence": "EXTRACTED", "source_file": "C:\\Users\\yashb\\Pictures\\Projects\\TestBuddy\\Frontend\\src\\components\\NavLink.tsx", "source_location": "L3", "weight": 1.0}], "raw_calls": []}