{"nodes": [{"id": "c_users_yashb_pictures_projects_testbuddy_frontend_src_pages_notifications_tsx", "label": "Notifications.tsx", "file_type": "code", "source_file": "C:\\Users\\yashb\\Pictures\\Projects\\TestBuddy\\Frontend\\src\\pages\\Notifications.tsx", "source_location": "L1"}, {"id": "notifications_markallread", "label": "markAllRead()", "file_type": "code", "source_file": "C:\\Users\\yashb\\Pictures\\Projects\\TestBuddy\\Frontend\\src\\pages\\Notifications.tsx", "source_location": "L37"}, {"id": "notifications_toggleread", "label": "toggleRead()", "file_type": "code", "source_file": "C:\\Users\\yashb\\Pictures\\Projects\\TestBuddy\\Frontend\\src\\pages\\Notifications.tsx", "source_location": "L41"}], "edges": [{"source": "c_users_yashb_pictures_projects_testbuddy_frontend_src_pages_notifications_tsx", "target": "react", "relation": "imports_from", "confidence": "EXTRACTED", "source_file": "C:\\Users\\yashb\\Pictures\\Projects\\TestBuddy\\Frontend\\src\\pages\\Notifications.tsx", "source_location": "L1", "weight": 1.0}, {"source": "c_users_yashb_pictures_projects_testbuddy_frontend_src_pages_notifications_tsx", "target": "lucide_react", "relation": "imports_from", "confidence": "EXTRACTED", "source_file": "C:\\Users\\yashb\\Pictures\\Projects\\TestBuddy\\Frontend\\src\\pages\\Notifications.tsx", "source_location": "L2", "weight": 1.0}, {"source": "c_users_yashb_pictures_projects_testbuddy_frontend_src_pages_notifications_tsx", "target": "card", "relation": "imports_from", "confidence": "EXTRACTED", "source_file": "C:\\Users\\yashb\\Pictures\\Projects\\TestBuddy\\Frontend\\src\\pages\\Notifications.tsx", "source_location": "L3", "weight": 1.0}, {"source": "c_users_yashb_pictures_projects_testbuddy_frontend_src_pages_notifications_tsx", "target": "button", "relation": "imports_from", "confidence": "EXTRACTED", "source_file": "C:\\Users\\yashb\\Pictures\\Projects\\TestBuddy\\Frontend\\src\\pages\\Notifications.tsx", "source_location": "L4", "weight": 1.0}, {"source": "c_users_yashb_pictures_projects_testbuddy_frontend_src_pages_notifications_tsx", "target": "utils", "relation": "imports_from", "confidence": "EXTRACTED", "source_file": "C:\\Users\\yashb\\Pictures\\Projects\\TestBuddy\\Frontend\\src\\pages\\Notifications.tsx", "source_location": "L5", "weight": 1.0}, {"source": "c_users_yashb_pictures_projects_testbuddy_frontend_src_pages_notifications_tsx", "target": "notifications_markallread", "relation": "contains", "confidence": "EXTRACTED", "source_file": "C:\\Users\\yashb\\Pictures\\Projects\\TestBuddy\\Frontend\\src\\pages\\Notifications.tsx", "source_location": "L37", "weight": 1.0}, {"source": "c_users_yashb_pictures_projects_testbuddy_frontend_src_pages_notifications_tsx", "target": "notifications_toggleread", "relation": "contains", "confidence": "EXTRACTED", "source_file": "C:\\Users\\yashb\\Pictures\\Projects\\TestBuddy\\Frontend\\src\\pages\\Notifications.tsx", "source_location": "L41", "weight": 1.0}], "raw_calls": [{"caller_nid": "notifications_markallread", "callee": "setItems", "source_file": "C:\\Users\\yashb\\Pictures\\Projects\\TestBuddy\\Frontend\\src\\pages\\Notifications.tsx", "source_location": "L38"}, {"caller_nid": "notifications_toggleread", "callee": "setItems", "source_file": "C:\\Users\\yashb\\Pictures\\Projects\\TestBuddy\\Frontend\\src\\pages\\Notifications.tsx", "source_location": "L42"}]}